coralogix/__init__.py
coralogix/constants.py
coralogix/coralogix_logger.py
coralogix/http.py
coralogix/manager.py
coralogix/handlers/__init__.py
coralogix/handlers/coralogix.py
coralogix/handlers/debug.py
coralogix/tests/__init__.py
coralogix/tests/test_constants.py
coralogix/tests/test_coralogix.py
coralogix/tests/test_debug.py
coralogix/tests/test_http.py
coralogix/tests/test_manager.py
coralogix/tests/helpers/__init__.py
coralogix/tests/helpers/case.py
coralogix_logger-2.0.7.dist-info/licenses/LICENSE
coralogix_logger-2.0.7.dist-info/METADATA
coralogix_logger-2.0.7.dist-info/WHEEL
coralogix_logger-2.0.7.dist-info/top_level.txt
coralogix_logger-2.0.7.dist-info/RECORD
