Metadata-Version: 2.4
Name: coralogix_logger
Version: 2.0.7
Summary: Coralogix Python SDK
Home-page: http://www.coralogix.com/
Download-URL: https://github.com/coralogix/python-coralogix-sdk/archive/master.zip
Author: Coralogix Ltd.
Author-email: info@coralogix.com
Maintainer: Coralogix Ltd.
Maintainer-email: info@coralogix.com
License: Apache Version 2.0
Keywords: Coralogix,Logging,Logger
Classifier: Development Status :: 5 - Production/Stable
Classifier: Natural Language :: English
Classifier: License :: OSI Approved :: Apache Software License
Classifier: Operating System :: OS Independent
Classifier: Intended Audience :: Developers
Classifier: Intended Audience :: System Administrators
Classifier: Intended Audience :: Manufacturing
Classifier: Intended Audience :: Telecommunications Industry
Classifier: Programming Language :: Python :: 3
Classifier: Programming Language :: Python :: 3.5
Classifier: Programming Language :: Python :: 3.6
Classifier: Programming Language :: Python :: 3.7
Classifier: Programming Language :: Python :: 3.8
Classifier: Programming Language :: Python :: Implementation :: PyPy
Classifier: Topic :: Internet :: Log Analysis
Classifier: Topic :: Software Development :: Libraries :: Python Modules
Classifier: Topic :: System :: Logging
Classifier: Topic :: System :: Monitoring
Classifier: Topic :: System :: Networking :: Monitoring
Classifier: Topic :: Utilities
Requires-Python: >=3.5
License-File: LICENSE
Requires-Dist: requests>=2.24.0
Provides-Extra: development
Requires-Dist: wheel>=0.31.0; extra == "development"
Requires-Dist: twine>=3.3.0; extra == "development"
Dynamic: author
Dynamic: author-email
Dynamic: classifier
Dynamic: description
Dynamic: download-url
Dynamic: home-page
Dynamic: keywords
Dynamic: license
Dynamic: license-file
Dynamic: maintainer
Dynamic: maintainer-email
Dynamic: provides-extra
Dynamic: requires-dist
Dynamic: requires-python
Dynamic: summary
